huaweicloudsdkdwr/__init__.py
huaweicloudsdkdwr/v1/__init__.py
huaweicloudsdkdwr/v1/dwr_async_client.py
huaweicloudsdkdwr/v1/dwr_client.py
huaweicloudsdkdwr/v1/model/__init__.py
huaweicloudsdkdwr/v1/model/build_progress.py
huaweicloudsdkdwr/v1/model/charge_info.py
huaweicloudsdkdwr/v1/model/collection_base_info.py
huaweicloudsdkdwr/v1/model/create_collection_body.py
huaweicloudsdkdwr/v1/model/create_collection_request.py
huaweicloudsdkdwr/v1/model/create_collection_response.py
huaweicloudsdkdwr/v1/model/create_index_body.py
huaweicloudsdkdwr/v1/model/create_index_request.py
huaweicloudsdkdwr/v1/model/create_index_response.py
huaweicloudsdkdwr/v1/model/create_store_body.py
huaweicloudsdkdwr/v1/model/create_store_data.py
huaweicloudsdkdwr/v1/model/create_store_request.py
huaweicloudsdkdwr/v1/model/create_store_response.py
huaweicloudsdkdwr/v1/model/decribe_collection_data.py
huaweicloudsdkdwr/v1/model/delete_collection_request.py
huaweicloudsdkdwr/v1/model/delete_collection_response.py
huaweicloudsdkdwr/v1/model/delete_entities_body.py
huaweicloudsdkdwr/v1/model/delete_entities_request.py
huaweicloudsdkdwr/v1/model/delete_entities_response.py
huaweicloudsdkdwr/v1/model/delete_index_body.py
huaweicloudsdkdwr/v1/model/delete_index_request.py
huaweicloudsdkdwr/v1/model/delete_index_response.py
huaweicloudsdkdwr/v1/model/delete_store_data.py
huaweicloudsdkdwr/v1/model/delete_store_request.py
huaweicloudsdkdwr/v1/model/delete_store_response.py
huaweicloudsdkdwr/v1/model/describe_collection_request.py
huaweicloudsdkdwr/v1/model/describe_collection_response.py
huaweicloudsdkdwr/v1/model/describe_index_body.py
huaweicloudsdkdwr/v1/model/describe_index_data.py
huaweicloudsdkdwr/v1/model/describe_index_request.py
huaweicloudsdkdwr/v1/model/describe_index_response.py
huaweicloudsdkdwr/v1/model/describe_job_body.py
huaweicloudsdkdwr/v1/model/describe_job_request.py
huaweicloudsdkdwr/v1/model/describe_job_response.py
huaweicloudsdkdwr/v1/model/describe_store_request.py
huaweicloudsdkdwr-3.1.184.dist-info/METADATA
huaweicloudsdkdwr-3.1.184.dist-info/WHEEL
huaweicloudsdkdwr-3.1.184.dist-info/licenses/LICENSE
huaweicloudsdkdwr-3.1.184.dist-info/RECORD
